mantarray_waveform_analysis/__init__.py
mantarray_waveform_analysis/compression_cy.cp39-win_amd64.pyd
mantarray_waveform_analysis/compression_cy.pyx
mantarray_waveform_analysis/constants.py
mantarray_waveform_analysis/exceptions.py
mantarray_waveform_analysis/peak_detection.py
mantarray_waveform_analysis/pipelines.py
mantarray_waveform_analysis/transforms.py
mantarray_waveform_analysis-1.2.0.dist-info/LICENSE
mantarray_waveform_analysis-1.2.0.dist-info/METADATA
mantarray_waveform_analysis-1.2.0.dist-info/WHEEL
mantarray_waveform_analysis-1.2.0.dist-info/top_level.txt
mantarray_waveform_analysis-1.2.0.dist-info/RECORD
