Metadata-Version: 2.1
Name: mantarray-waveform-analysis
Version: 1.2.0
Summary: Tools for analyzing waveforms produced by a Mantarray Instrument
Home-page: https://github.com/CuriBio/mantarray-waveform-analysis
Author: Curi Bio
Author-email: contact@curibio.com
License: MIT
Platform: UNKNOWN
Classifier: Development Status :: 1 - Planning
Classifier: Intended Audience :: Science/Research
Classifier: License :: OSI Approved :: MIT License
Classifier: Programming Language :: Python
Classifier: Programming Language :: Python :: 3
Classifier: Programming Language :: Python :: 3.7
Classifier: Programming Language :: Python :: 3.8
Classifier: Programming Language :: Python :: 3.9
Classifier: Topic :: Scientific/Engineering
License-File: LICENSE
